vsd-riscv2-TASK-2/RTL/gpio_ip.v
// ============================================================
//  Simple GPIO Output IP  (Write-Only, Memory-Mapped)
//  
//  Bus Interface : Custom SOC bus (same as LED / UART peripherals)
//  Address       : IO page, 1-hot word address bit 3
//                  → effective address  0x00400008  (bit 22 = IO,
//                                                    word addr bit 3)
//  Register map  :
//    Offset 0x00 (the only register)
//      [31:0]  gpio_reg  –  written by CPU, drives gpio_out[31:0]
//                           read-back returns last written value
//
//  Signals that connect to SOC top-level
//    clk         – system clock  (from Clockworks)
//    resetn      – active-low reset
//    mem_wordaddr– mem_addr[31:2]  (29-bit word address from CPU)
//    isIO        – mem_addr[22]    (IO-page select from SOC)
//    mem_wstrb   – |mem_wmask      (any byte write active)
//    mem_wdata   – 32-bit write data from CPU
//    gpio_rdata  – 32-bit read data back to IO_rdata mux
//    gpio_out    – 32-bit output port (connect to LEDs / pins)
// ============================================================

`default_nettype none

module gpio_ip (
    input  wire        clk,
    input  wire        resetn,

    // --- Bus interface (same signals already in SOC) ----------
    input  wire [29:0] mem_wordaddr, // mem_addr[31:2]
    input  wire        isIO,         // mem_addr[22]
    input  wire        mem_wstrb,    // |mem_wmask
    input  wire [31:0] mem_wdata,    // write data from CPU

    // --- Read-back to IO_rdata mux ---------------------------
    output wire [31:0] gpio_rdata,

    // --- Actual GPIO output port ------------------------------
    output wire [31:0] gpio_out
);

    // ----------------------------------------------------------
    // 1-hot address bit for this peripheral
    //   bit 0 → LEDS
    //   bit 1 → UART_DAT
    //   bit 2 → UART_CNTL
    //   bit 3 → GPIO   ← this IP
    // ----------------------------------------------------------
    localparam IO_GPIO_bit = 3;

    // Decode: this peripheral is selected when IO page is active
    // AND word-address bit 3 is set
    wire gpio_sel_w = isIO & mem_wstrb  & mem_wordaddr[IO_GPIO_bit];
    wire gpio_sel_r = isIO & (~mem_wstrb) & mem_wordaddr[IO_GPIO_bit];

    // ----------------------------------------------------------
    // The single 32-bit register
    // ----------------------------------------------------------
    reg [31:0] gpio_reg;

    always @(posedge clk) begin
        if (!resetn) begin
            gpio_reg <= 32'b0;          // clear on reset
        end else if (gpio_sel_w) begin
            gpio_reg <= mem_wdata;      // CPU write updates the register
        end
    end

    // ----------------------------------------------------------
    // Read-back  (combinational – mirrors SOC IO_rdata pattern)
    // Returns last written value when CPU reads this address,
    // returns 0 otherwise (so it can be OR-ed safely in the mux)
    // ----------------------------------------------------------
    assign gpio_rdata = mem_wordaddr[IO_GPIO_bit] ? gpio_reg : 32'b0;

    // ----------------------------------------------------------
    // Output port – continuously reflects the register value
    // ----------------------------------------------------------
    assign gpio_out = gpio_reg;

endmodule

vsd-riscv2-TASK-2/RTL/tb_gpio.v
// ============================================================
//  tb_gpio.v  —  Testbench for GPIO IP (Step 4 Simulation)
//
//  Tests:
//    1. Direct gpio_ip module tests (unit test)
//    2. Waveform dumped to gpio_wave.vcd  (open in GTKWave)
//
//  Run with:
//    iverilog -o tb_gpio gpio_ip.v tb_gpio.v && vvp tb_gpio
// ============================================================

`timescale 1ns/1ps
`default_nettype none
`include "gpio_ip.v"

module tb_gpio;

    // --------------------------------------------------------
    // Clock & reset
    // --------------------------------------------------------
    reg clk    = 0;
    reg resetn = 0;

    always #5 clk = ~clk;  // 100 MHz clock (10ns period)

    // --------------------------------------------------------
    // DUT (Device Under Test) signals  — match gpio_ip ports
    // --------------------------------------------------------
    reg  [29:0] mem_wordaddr;
    reg         isIO;
    reg         mem_wstrb;
    reg  [31:0] mem_wdata;

    wire [31:0] gpio_rdata;
    wire [31:0] gpio_out;

    // --------------------------------------------------------
    // Instantiate gpio_ip
    // --------------------------------------------------------
    gpio_ip DUT (
        .clk         (clk),
        .resetn      (resetn),
        .mem_wordaddr(mem_wordaddr),
        .isIO        (isIO),
        .mem_wstrb   (mem_wstrb),
        .mem_wdata   (mem_wdata),
        .gpio_rdata  (gpio_rdata),
        .gpio_out    (gpio_out)
    );

    // --------------------------------------------------------
    // VCD waveform dump  →  gpio_wave.vcd
    // Open with: gtkwave gpio_wave.vcd
    // --------------------------------------------------------
    initial begin
        $dumpfile("gpio_wave.vcd");
        $dumpvars(0, tb_gpio);  // dump ALL signals in this tb
    end

    // --------------------------------------------------------
    // Test tracking
    // --------------------------------------------------------
    integer pass_count = 0;
    integer fail_count = 0;

    // --------------------------------------------------------
    // Task: write a value to GPIO register
    //   IO_GPIO_bit = 3  →  mem_wordaddr bit 3 must be set
    //   GPIO address = 0x00400010 → word addr = 0x00100004
    //   bit 3 of word addr = 1  ✓
    // --------------------------------------------------------
    task gpio_write;
        input [31:0] data;
        begin
            @(negedge clk);          // change on falling edge
            mem_wordaddr = 30'b1000; // bit 3 set = GPIO select
            isIO         = 1'b1;
            mem_wstrb    = 1'b1;
            mem_wdata    = data;
            @(posedge clk);          // latch happens here
            #1;                      // small settle time
            mem_wstrb    = 1'b0;     // deassert write strobe
            isIO         = 1'b0;
        end
    endtask

    // --------------------------------------------------------
    // Task: check gpio_out and gpio_rdata, print PASS/FAIL
    // --------------------------------------------------------
    task check_gpio;
        input [31:0] expected;
        input [63:0] test_num;  // test number for display
        begin
            // gpio_out is combinational — check immediately
            // gpio_rdata also combinational when wordaddr[3]=1
            mem_wordaddr = 30'b1000; // keep bit 3 high for read
            isIO         = 1'b1;
            mem_wstrb    = 1'b0;     // read, not write
            #1;                      // let combinational settle

            $write("Test %0d | wrote 0x%08X | gpio_out=0x%08X | gpio_rdata=0x%08X | ",
                   test_num, expected, gpio_out, gpio_rdata);

            if (gpio_out === expected && gpio_rdata === expected) begin
                $display("PASS");
                pass_count = pass_count + 1;
            end else begin
                $display("FAIL  *** expected 0x%08X ***", expected);
                fail_count = fail_count + 1;
            end

            isIO = 1'b0;
        end
    endtask

    // --------------------------------------------------------
    // Main test sequence
    // --------------------------------------------------------
    initial begin
        // initialise inputs
        mem_wordaddr = 0;
        isIO         = 0;
        mem_wstrb    = 0;
        mem_wdata    = 0;

        // ---- Reset sequence --------------------------------
        resetn = 0;
        repeat(4) @(posedge clk);
        resetn = 1;
        repeat(2) @(posedge clk);

        $display("============================================");
        $display("   GPIO IP Testbench — Starting Tests");
        $display("============================================");

        // ---- Check reset state ------------------------------
        $write("Reset check  | gpio_out after reset = 0x%08X | ", gpio_out);
        if (gpio_out === 32'h0) begin
            $display("PASS (cleared to 0)");
            pass_count = pass_count + 1;
        end else begin
            $display("FAIL (expected 0x00000000)");
            fail_count = fail_count + 1;
        end

        // ---- Test 1: All zeros ------------------------------
        gpio_write(32'h00000000);
        check_gpio(32'h00000000, 1);

        // ---- Test 2: All ones -------------------------------
        gpio_write(32'hFFFFFFFF);
        check_gpio(32'hFFFFFFFF, 2);

        // ---- Test 3: LSB only (walking 1 low) ---------------
        gpio_write(32'h00000001);
        check_gpio(32'h00000001, 3);

        // ---- Test 4: MSB only (walking 1 high) --------------
        gpio_write(32'h80000000);
        check_gpio(32'h80000000, 4);

        // ---- Test 5: Alternating 0xAA -----------------------
        gpio_write(32'hAAAAAAAA);
        check_gpio(32'hAAAAAAAA, 5);

        // ---- Test 6: Alternating 0x55 -----------------------
        gpio_write(32'h55555555);
        check_gpio(32'h55555555, 6);

        // ---- Test 7: Meaningful value -----------------------
        gpio_write(32'hDEADBEEF);
        check_gpio(32'hDEADBEEF, 7);

        // ---- Test 8: Overwrite — value should update --------
        gpio_write(32'hCAFEBABE);
        gpio_write(32'h12345678); // overwrite with new value
        check_gpio(32'h12345678, 8);

        // ---- Test 9: Verify no write when isIO=0 ------------
        // gpio holds 0x12345678 from test 8
        // attempt a write with isIO=0 — register must NOT change
        @(negedge clk);
        mem_wordaddr = 30'b1000;
        isIO         = 1'b0;    // IO NOT selected
        mem_wstrb    = 1'b1;
        mem_wdata    = 32'hBAD0BAD0;
        @(posedge clk);
        #1;
        mem_wstrb = 1'b0;

        $write("Test 9  | isIO=0 write ignored check  | gpio_out=0x%08X | ", gpio_out);
        if (gpio_out === 32'h12345678) begin
            $display("PASS (register unchanged)");
            pass_count = pass_count + 1;
        end else begin
            $display("FAIL (register was incorrectly overwritten!)");
            fail_count = fail_count + 1;
        end

        // ---- Summary ----------------------------------------
        repeat(2) @(posedge clk);
        $display("============================================");
        $display("   Results: %0d PASSED,  %0d FAILED", pass_count, fail_count);
        $display("   Waveform saved to: gpio_wave.vcd");
        $display("============================================");

        $finish;
    end

    // --------------------------------------------------------
    // Timeout watchdog — prevents infinite loops
    // --------------------------------------------------------
    initial begin
        #10000;
        $display("TIMEOUT — simulation exceeded 10us");
        $finish;
    end

endmodule

vsd-riscv2-TASK-2/RTL/gpio_wave.vcd
$date
	Fri Apr 24 14:40:16 2026
$end
$version
	Icarus Verilog
$end
$timescale
	1ps
$end
$scope module tb_gpio $end
$var wire 32 ! gpio_out [31:0] $end
$var wire 32 " gpio_rdata [31:0] $end
$var reg 1 # clk $end
$var integer 32 $ fail_count [31:0] $end
$var reg 1 % isIO $end
$var reg 32 & mem_wdata [31:0] $end
$var reg 30 ' mem_wordaddr [29:0] $end
$var reg 1 ( mem_wstrb $end
$var integer 32 ) pass_count [31:0] $end
$var reg 1 * resetn $end
$scope module DUT $end
$var wire 1 + clk $end
$var wire 32 , gpio_out [31:0] $end
$var wire 32 - gpio_rdata [31:0] $end
$var wire 1 . gpio_sel_r $end
$var wire 1 / gpio_sel_w $end
$var wire 1 0 isIO $end
$var wire 32 1 mem_wdata [31:0] $end
$var wire 30 2 mem_wordaddr [29:0] $end
$var wire 1 3 mem_wstrb $end
$var wire 1 4 resetn $end
$var reg 32 5 gpio_reg [31:0] $end
$upscope $end
$scope task check_gpio $end
$var reg 32 6 expected [31:0] $end
$var reg 64 7 test_num [63:0] $end
$upscope $end
$scope task gpio_write $end
$var reg 32 8 data [31:0] $end
$upscope $end
$upscope $end
$enddefinitions $end
#0
$dumpvars
bx 8
bx 7
bx 6
bx 5
04
03
b0 2
b0 1
00
0/
0.
b0 -
bx ,
0+
0*
b0 )
0(
b0 '
b0 &
0%
b0 $
0#
b0 "
bx !
$end
#5000
b0 5
b0 !
b0 ,
1#
1+
#10000
0#
0+
#15000
1#
1+
#20000
0#
0+
#25000
1#
1+
#30000
0#
0+
#35000
1*
14
1#
1+
#40000
0#
0+
#45000
1#
1+
#50000
0#
0+
#55000
b0 8
b1 )
1#
1+
#60000
1/
0.
1(
13
1%
10
b1000 '
b1000 2
0#
0+
#65000
1#
1+
#66000
1.
0/
b1 7
b0 6
1%
10
0(
03
#67000
0.
b11111111111111111111111111111111 8
0%
00
b10 )
#70000
1/
0.
b11111111111111111111111111111111 &
b11111111111111111111111111111111 1
1(
13
1%
10
0#
0+
#75000
b11111111111111111111111111111111 "
b11111111111111111111111111111111 -
b11111111111111111111111111111111 5
b11111111111111111111111111111111 !
b11111111111111111111111111111111 ,
1#
1+
#76000
1.
0/
b10 7
b11111111111111111111111111111111 6
1%
10
0(
03
#77000
0.
b1 8
0%
00
b11 )
#80000
1/
0.
b1 &
b1 1
1(
13
1%
10
0#
0+
#85000
b1 "
b1 -
b1 5
b1 !
b1 ,
1#
1+
#86000
1.
0/
b11 7
b1 6
1%
10
0(
03
#87000
0.
b10000000000000000000000000000000 8
0%
00
b100 )
#90000
1/
0.
b10000000000000000000000000000000 &
b10000000000000000000000000000000 1
1(
13
1%
10
0#
0+
#95000
b10000000000000000000000000000000 "
b10000000000000000000000000000000 -
b10000000000000000000000000000000 5
b10000000000000000000000000000000 !
b10000000000000000000000000000000 ,
1#
1+
#96000
1.
0/
b100 7
b10000000000000000000000000000000 6
1%
10
0(
03
#97000
0.
b10101010101010101010101010101010 8
0%
00
b101 )
#100000
1/
0.
b10101010101010101010101010101010 &
b10101010101010101010101010101010 1
1(
13
1%
10
0#
0+
#105000
b10101010101010101010101010101010 "
b10101010101010101010101010101010 -
b10101010101010101010101010101010 5
b10101010101010101010101010101010 !
b10101010101010101010101010101010 ,
1#
1+
#106000
1.
0/
b101 7
b10101010101010101010101010101010 6
1%
10
0(
03
#107000
0.
b1010101010101010101010101010101 8
0%
00
b110 )
#110000
1/
0.
b1010101010101010101010101010101 &
b1010101010101010101010101010101 1
1(
13
1%
10
0#
0+
#115000
b1010101010101010101010101010101 "
b1010101010101010101010101010101 -
b1010101010101010101010101010101 5
b1010101010101010101010101010101 !
b1010101010101010101010101010101 ,
1#
1+
#116000
1.
0/
b110 7
b1010101010101010101010101010101 6
1%
10
0(
03
#117000
0.
b11011110101011011011111011101111 8
0%
00
b111 )
#120000
1/
0.
b11011110101011011011111011101111 &
b11011110101011011011111011101111 1
1(
13
1%
10
0#
0+
#125000
b11011110101011011011111011101111 "
b11011110101011011011111011101111 -
b11011110101011011011111011101111 5
b11011110101011011011111011101111 !
b11011110101011011011111011101111 ,
1#
1+
#126000
1.
0/
b111 7
b11011110101011011011111011101111 6
1%
10
0(
03
#127000
0.
b11001010111111101011101010111110 8
0%
00
b1000 )
#130000
1/
0.
b11001010111111101011101010111110 &
b11001010111111101011101010111110 1
1(
13
1%
10
0#
0+
#135000
b11001010111111101011101010111110 "
b11001010111111101011101010111110 -
b11001010111111101011101010111110 5
b11001010111111101011101010111110 !
b11001010111111101011101010111110 ,
1#
1+
#136000
0/
b10010001101000101011001111000 8
0%
00
0(
03
#140000
1/
0.
b10010001101000101011001111000 &
b10010001101000101011001111000 1
1(
13
1%
10
0#
0+
#145000
b10010001101000101011001111000 "
b10010001101000101011001111000 -
b10010001101000101011001111000 5
b10010001101000101011001111000 !
b10010001101000101011001111000 ,
1#
1+
#146000
1.
0/
b1000 7
b10010001101000101011001111000 6
1%
10
0(
03
#147000
0.
0%
00
b1001 )
#150000
b10111010110100001011101011010000 &
b10111010110100001011101011010000 1
1(
13
0#
0+
#155000
1#
1+
#156000
b1010 )
0(
03
